README.md
setup.py
redis_record/__init__.py
redis_record/__main__.py
redis_record/cmd.py
redis_record/config.py
redis_record/fake.py
redis_record/sync.py
redis_record/util.py
redis_record/watch.py
redis_record.egg-info/PKG-INFO
redis_record.egg-info/SOURCES.txt
redis_record.egg-info/dependency_links.txt
redis_record.egg-info/entry_points.txt
redis_record.egg-info/requires.txt
redis_record.egg-info/top_level.txt
redis_record/record/__init__.py
redis_record/record/__main__.py
redis_record/record/monitor.py
redis_record/record/streams.py
redis_record/replay/__init__.py
redis_record/replay/__main__.py
redis_record/replay/monitor.py
redis_record/replay/streams.py
redis_record/storage/__init__.py
redis_record/storage/info/__init__.py
redis_record/storage/info/mcap.py
redis_record/storage/info/zip.py
redis_record/storage/recorder/__init__.py
redis_record/storage/recorder/base.py
redis_record/storage/recorder/json.py
redis_record/storage/recorder/mcap.py
redis_record/storage/recorder/zip.py
redis_record/storage/replay/__init__.py
redis_record/storage/replay/base.py
redis_record/storage/replay/mcap.py
redis_record/storage/replay/zip.py