Metadata-Version: 2.1
Name: redis-record
Version: 0.0.4
Summary: redis streams recordings
Home-page: https://github.com/beasteers/redis-record
Author: Bea Steers
Author-email: bea.steers@gmail.com
License: MIT License
Keywords: redis record streams video streaming
